envfileparser/__init__.py
envfileparser/get_env.py
envfileparser/get_env_from_file.py
envfileparser/get_envs.py
envfileparser/parse_env.py
envfileparser/read_env.py
envfileparser-0.0.8.dist-info/LICENSE
envfileparser-0.0.8.dist-info/METADATA
envfileparser-0.0.8.dist-info/WHEEL
envfileparser-0.0.8.dist-info/top_level.txt
envfileparser-0.0.8.dist-info/RECORD
