Metadata-Version: 2.1
Name: envfileparser
Version: 0.0.8
Summary: A small env file parser
Home-page: https://github.com/kirilllapushinskiy/py-env-file-parser
Author: Kirill Lapushinskiy
Author-email: kirilllapushinskiy@yahoo.com
License: UNKNOWN
Project-URL: Bug Tracker, https://github.com/kirilllapushinskiy/py-env-file-parser/issues
Platform: UNKNOWN
Classifier: Programming Language :: Python :: 3
Classifier: License :: OSI Approved :: GNU General Public License v3 (GPLv3)
Classifier: Operating System :: OS Independent
Requires-Python: >=3.6
License-File: LICENSE
